README.md
outsourcer.py
requirements-dev.txt
setup.py
outsourcer.egg-info/PKG-INFO
outsourcer.egg-info/SOURCES.txt
outsourcer.egg-info/dependency_links.txt
outsourcer.egg-info/top_level.txt