Metadata-Version: 2.1
Name: outsourcer
Version: 0.0.1
Summary: Build and test your Python examples
Home-page: https://github.com/jvs/outsourcer
Author: jvs
Author-email: vonseg@protonmail.com
License: MIT License
Keywords: code-generation
Platform: any
Classifier: Development Status :: 2 - Pre-Alpha
Classifier: License :: OSI Approved :: MIT License
Classifier: Programming Language :: Python
Requires-Python: >=3.6
